thcouch/__init__.py
thcouch/core/__init__.py
thcouch/core/attachment/__init__.py
thcouch/core/attachment/delete.py
thcouch/core/attachment/get.py
thcouch/core/attachment/head.py
thcouch/core/attachment/put.py
thcouch/core/attachment/unwrap.py
thcouch/core/db/__init__.py
thcouch/core/db/all_docs.py
thcouch/core/db/bulk_docs.py
thcouch/core/db/bulk_get.py
thcouch/core/db/delete.py
thcouch/core/db/design_docs/__init__.py
thcouch/core/db/design_docs/get.py
thcouch/core/db/design_docs/post.py
thcouch/core/db/design_docs/unwrap.py
thcouch/core/db/find.py
thcouch/core/db/get.py
thcouch/core/db/head.py
thcouch/core/db/post.py
thcouch/core/db/put.py
thcouch/core/db/unwrap.py
thcouch/core/doc/__init__.py
thcouch/core/doc/delete.py
thcouch/core/doc/get.py
thcouch/core/doc/head.py
thcouch/core/doc/put.py
thcouch/core/doc/unwrap.py
thcouch/core/index/__init__.py
thcouch/core/index/delete.py
thcouch/core/index/get.py
thcouch/core/index/post.py
thcouch/core/index/unwrap.py
thcouch/core/server/__init__.py
thcouch/core/server/all_dbs.py
thcouch/core/server/dbs_info.py
thcouch/core/server/server.py
thcouch/core/server/unwrap.py
thcouch/orm/__init__.py
thcouch/orm/_common.py
thcouch/orm/_error.py
thcouch/orm/attachment.py
thcouch/orm/client.py
thcouch/orm/database.py
thcouch/orm/decl/__init__.py
thcouch/orm/decl/error.py
thcouch/orm/decl/field.py
thcouch/orm/decl/index.py
thcouch/orm/decl/loader.py
thcouch/orm/decl/model.py
thcouch/orm/decl/object.py
thcouch/orm/decl/unwrap.py
thcouch/orm/decl/validator.py
thcouch/orm/document.py
thcouch/orm/index.py
thcouch-0.9.21.dist-info/LICENSE
thcouch-0.9.21.dist-info/METADATA
thcouch-0.9.21.dist-info/WHEEL
thcouch-0.9.21.dist-info/RECORD
