Metadata-Version: 2.1
Name: thcouch
Version: 0.9.21
Summary: Tangled thcouch library
Home-page: https://gitlab.com/tangledlabs/thcouch
License: BSD 3-clause
Keywords: tangled,tangledhub,tangledcloud,tangledlab,tangledgroup,thcouch,couchdb,couch
Author: Tangled
Author-email: info@tangledgroup.com
Requires-Python: >=3.10,<4.0
Classifier: Development Status :: 4 - Beta
Classifier: Intended Audience :: Developers
Classifier: License :: OSI Approved :: BSD License
Classifier: License :: Other/Proprietary License
Classifier: Operating System :: OS Independent
Classifier: Programming Language :: Python
Classifier: Programming Language :: Python :: 3
Classifier: Programming Language :: Python :: 3.10
Classifier: Programming Language :: Python :: 3.11
Classifier: Programming Language :: Python :: 3.10
Classifier: Programming Language :: Python :: 3.11
Classifier: Topic :: Database
Classifier: Topic :: Database :: Database Engines/Servers
Requires-Dist: aiohttp (>=3.8.3,<4.0.0)
Requires-Dist: json5 (>=0.9.10,<0.10.0)
Requires-Dist: pyyaml (>=6.0,<7.0)
Requires-Dist: pyyaml-include (>=1.3,<2.0)
Requires-Dist: thresult (>=0.9.14,<0.10.0)
Requires-Dist: toml (>=0.10.2,<0.11.0)
Project-URL: Repository, https://gitlab.com/tangledlabs/thcouch
